[
  {
    "alpha_id": "ALPHA16879",
    "source": "r/SideProject",
    "source_url": "https://www.reddit.com/r/SideProject/comments/1rmt78d/i_built_terraink_an_opensource_tool_for_instant/",
    "tactic": "I built TerraInk, an open-source tool for instant and fully customizable map posters rendering",
    "category": "PRODUCT_LAUNCH",
    "roi_potential": "MEDIUM",
    "status": "PENDING_REVIEW",
    "engagement_authenticity": "AUTHENTIC",
    "earnings_verified": "N/A",
    "created_at": "2026-03-07T02:54:05.833460",
    "notes": "Score: 234, Comments: 19"
  },
  {
    "alpha_id": "ALPHA16880",
    "source": "r/coldemail",
    "source_url": "https://www.reddit.com/r/coldemail/comments/1rm8ied/best_way_to_scale_outbound_prospecting_when_youre/",
    "tactic": "Best way to scale outbound prospecting when you\u2019re a small team?",
    "category": "COLD_OUTBOUND",
    "roi_potential": "LOW",
    "status": "PENDING_REVIEW",
    "engagement_authenticity": "UNCHECKED",
    "earnings_verified": "N/A",
    "created_at": "2026-03-07T02:54:14.143563",
    "notes": "Score: 10, Comments: 7"
  },
  {
    "alpha_id": "ALPHA16881",
    "source": "r/growthhacking",
    "source_url": "https://www.reddit.com/r/GrowthHacking/comments/1rl97pi/whats_an_unconventional_marketing_tactic_that/",
    "tactic": "What\u2019s an unconventional marketing tactic that surprisingly worked for you?",
    "category": "GROWTH_TACTICS",
    "roi_potential": "LOW",
    "status": "PENDING_REVIEW",
    "engagement_authenticity": "UNCHECKED",
    "earnings_verified": "N/A",
    "created_at": "2026-03-07T02:54:21.576004",
    "notes": "Score: 5, Comments: 18"
  },
  {
    "alpha_id": "ALPHA16882",
    "source": "r/InternetIsBeautiful",
    "source_url": "https://www.reddit.com/r/InternetIsBeautiful/comments/1rn18pw/i_made_a_website_where_anyone_can_draw_on_street/",
    "tactic": "I made a website where anyone can draw on Street View to create a massive, global community art project.",
    "category": "PRODUCT_DISCOVERY",
    "roi_potential": "LOW",
    "status": "PENDING_REVIEW",
    "engagement_authenticity": "AUTHENTIC",
    "earnings_verified": "N/A",
    "created_at": "2026-03-07T02:54:43.324040",
    "notes": "Score: 11, Comments: 7"
  },
  {
    "alpha_id": "ALPHA16883",
    "source": "r/InternetIsBeautiful",
    "source_url": "https://www.reddit.com/r/InternetIsBeautiful/comments/1rn1smx/i_built_a_free_youtube_tool_that_downloads_only/",
    "tactic": "I built a free YouTube tool that downloads only the seconds you actually want",
    "category": "PRODUCT_DISCOVERY",
    "roi_potential": "LOW",
    "status": "PENDING_REVIEW",
    "engagement_authenticity": "UNCHECKED",
    "earnings_verified": "N/A",
    "created_at": "2026-03-07T02:54:43.324068",
    "notes": "Score: 8, Comments: 0"
  },
  {
    "alpha_id": "ALPHA16884",
    "source": "r/InternetIsBeautiful",
    "source_url": "https://www.reddit.com/r/InternetIsBeautiful/comments/1rn1qvh/sigint_worldwatch_a_realtime_geopolitical/",
    "tactic": "SIGINT WorldWatch \u2014 a real-time geopolitical intelligence terminal I built and just launched \ud83c\udf0d",
    "category": "PRODUCT_DISCOVERY",
    "roi_potential": "LOW",
    "status": "PENDING_REVIEW",
    "engagement_authenticity": "UNCHECKED",
    "earnings_verified": "N/A",
    "created_at": "2026-03-07T02:54:43.324082",
    "notes": "Score: 5, Comments: 2"
  },
  {
    "alpha_id": "ALPHA16885",
    "source": "r/productivity",
    "source_url": "https://www.reddit.com/r/productivity/comments/1rmgo06/i_kept_blaming_myself_for_being_unproductive_but/",
    "tactic": "I kept blaming myself for being unproductive but it was actually just my apartment",
    "category": "PRODUCTIVITY_TOOLS",
    "roi_potential": "MEDIUM",
    "status": "PENDING_REVIEW",
    "engagement_authenticity": "AUTHENTIC",
    "earnings_verified": "N/A",
    "created_at": "2026-03-07T02:54:48.239773",
    "notes": "Score: 71, Comments: 6"
  }
]