[
  {
    "alpha_id": "ALPHA25412",
    "source": "r/coldemail",
    "source_url": "https://www.reddit.com/r/coldemail/comments/1rtmne4/i_built_a_google_maps_lead_scraper_with/",
    "tactic": "I built a Google Maps lead scraper with verification for emails and phone numbers",
    "category": "COLD_OUTBOUND",
    "roi_potential": "LOW",
    "status": "PENDING_REVIEW",
    "engagement_authenticity": "AUTHENTIC",
    "earnings_verified": "N/A",
    "created_at": "2026-03-14T12:19:39.794711",
    "notes": "Score: 21, Comments: 3"
  },
  {
    "alpha_id": "ALPHA25413",
    "source": "r/bigseo",
    "source_url": "https://www.reddit.com/r/bigseo/comments/1rtlqty/waiting_on_google_3_months_now_for_indexing_what/",
    "tactic": "Waiting on Google 3 months now for indexing... what more can I do?",
    "category": "SEO_ADVANCED",
    "roi_potential": "LOW",
    "status": "PENDING_REVIEW",
    "engagement_authenticity": "UNCHECKED",
    "earnings_verified": "N/A",
    "created_at": "2026-03-14T12:19:54.159106",
    "notes": "Score: 0, Comments: 0"
  },
  {
    "alpha_id": "ALPHA25414",
    "source": "r/Emailmarketing",
    "source_url": "https://www.reddit.com/r/Emailmarketing/comments/1rsnyoe/all_private_constant_contact_email_campaigns/",
    "tactic": "ALL PRIVATE Constant Contact email campaigns / events  searchable on Bing.",
    "category": "EMAIL_DELIVERABILITY",
    "roi_potential": "LOW",
    "status": "PENDING_REVIEW",
    "engagement_authenticity": "UNCHECKED",
    "earnings_verified": "N/A",
    "created_at": "2026-03-14T12:20:01.266341",
    "notes": "Score: 4, Comments: 3"
  }
]