{
  "name": "integration_kinda_in_2014_i_made_5kmo_with_nomad_",
  "created": "2026-03-24T18:50:47.596282",
  "method": "Kinda, in 2014 I made $5K/mo with Nomad List, 2015 was $10K/mo with Remote OK added\nBefore that 2008-2013, I was making anywhere from $2K to $8K/mo with my YouTube channel\nAnd then before 2008 I was m",
  "venture": "CONTENT",
  "phases": [
    {
      "name": "discover",
      "steps": [
        "scan_underserved_niches",
        "score_competition_gap",
        "validate_search_volume"
      ],
      "parallel": true
    },
    {
      "name": "build",
      "steps": [
        "generate_static_html_site",
        "inject_adsense_slots",
        "add_featured_listing_waitlist"
      ],
      "parallel": false,
      "depends_on": "discover"
    },
    {
      "name": "distribute",
      "steps": [
        "surge_deploy",
        "cross_link_from_47_live_apps",
        "submit_sitemap_google",
        "post_to_niche_subreddit"
      ],
      "parallel": true,
      "depends_on": "build"
    }
  ],
  "status": "READY"
}